kube_bench_report_converter_2/__init__.py
kube_bench_report_converter_2/command_line.py
kube_bench_report_converter_2/parser.py
kube_bench_report_converter_2/writer.py
kube_bench_report_converter_2-0.0.3.dist-info/licenses/LICENSE
kube_bench_report_converter_2-0.0.3.dist-info/METADATA
kube_bench_report_converter_2-0.0.3.dist-info/WHEEL
kube_bench_report_converter_2-0.0.3.dist-info/entry_points.txt
kube_bench_report_converter_2-0.0.3.dist-info/top_level.txt
kube_bench_report_converter_2-0.0.3.dist-info/RECORD
