Metadata-Version: 2.4
Name: kube-bench-report-converter-2
Version: 0.0.3
Summary: Converts kube-bench checks console output to CSV.
Author-email: Patrick Joyce <pjaudiomv@gmail.com>
Maintainer-email: Patrick Joyce <pjaudiomv@gmail.com>
License-Expression: MIT
Project-URL: Homepage, https://github.com/pjaudiomv/kube-bench-report-converter-2
Project-URL: Bug Tracker, https://github.com/pjaudiomv/kube-bench-report-converter-2/issues
Project-URL: Source Code, https://github.com/pjaudiomv/kube-bench-report-converter-2
Keywords: kube-bench,report,convert,csv
Classifier: Programming Language :: Python :: 3.9
Classifier: Programming Language :: Python :: 3.10
Classifier: Programming Language :: Python :: 3.11
Classifier: Programming Language :: Python :: 3.12
Classifier: Programming Language :: Python :: 3.13
Classifier: Operating System :: OS Independent
Requires-Python: >=3.9
License-File: LICENSE
Provides-Extra: dev
Requires-Dist: pytest>=7.0.0; extra == "dev"
Requires-Dist: pytest-cov>=4.0.0; extra == "dev"
Requires-Dist: black>=23.0.0; extra == "dev"
Requires-Dist: isort>=5.12.0; extra == "dev"
Dynamic: license-file
